pytil/__init__.py
pytil/algorithms.py
pytil/click.py
pytil/configuration.py
pytil/data_frame.py
pytil/debug.py
pytil/dict.py
pytil/difflib.py
pytil/exceptions.py
pytil/hashlib.py
pytil/iterable.py
pytil/logging.py
pytil/multi_dict.py
pytil/numpy.py
pytil/observable.py
pytil/parse.py
pytil/path.py
pytil/pkg_resources.py
pytil/series.py
pytil/set.py
pytil/sqlalchemy.py
pytil/various.py
pytil/write.py
pytil/test/__init__.py
pytil/test/_various.py
pytil/test/_xlsx.py
pytil/tests/__init__.py
pytil/tests/conftest.py
pytil/tests/test_algorithms.py
pytil/tests/test_click.py
pytil/tests/test_configuration.py
pytil/tests/test_data_frame.py
pytil/tests/test_debug.py
pytil/tests/test_dict.py
pytil/tests/test_hashlib.py
pytil/tests/test_iterable.py
pytil/tests/test_logging.py
pytil/tests/test_multi_dict.py
pytil/tests/test_observable.py
pytil/tests/test_path.py
pytil/tests/test_pkg_resources.py
pytil/tests/test_series.py
pytil/tests/test_set.py
pytil/tests/test_sqlalchemy.py
pytil/tests/test_test.py
pytil-7.0.0.dist-info/DESCRIPTION.rst
pytil-7.0.0.dist-info/METADATA
pytil-7.0.0.dist-info/RECORD
pytil-7.0.0.dist-info/WHEEL
pytil-7.0.0.dist-info/metadata.json
pytil-7.0.0.dist-info/top_level.txt
